my_feed/VERSION
my_feed/__init__.py
my_feed/my_feed.py
my_feed/version.py
my_feed/modules/__init__.py
my_feed/modules/post.py
my_feed/modules/settings.py
my_feed/modules/types.py
my_feed/platforms/__init__.py
my_feed/platforms/reddit.py
my_feed/platforms/twitter.py
my_feed/platforms/instagram/__init__.py
my_feed/platforms/instagram/credentials.py
my_feed/platforms/instagram/login.py
my_feed-0.0.6.dist-info/LICENSE
my_feed-0.0.6.dist-info/METADATA
my_feed-0.0.6.dist-info/WHEEL
my_feed-0.0.6.dist-info/top_level.txt
my_feed-0.0.6.dist-info/RECORD
