Metadata-Version: 2.1
Name: my-feed
Version: 0.0.6
Summary: A single service to get all your feed
Home-page: https://github.com/HoodyH/My-Feed
Author: HoodyH
License: LGPLv3
Platform: UNKNOWN
Classifier: Programming Language :: Python
Classifier: License :: OSI Approved :: GNU General Public License v3 (GPLv3)
Requires-Python: >=3.7
Requires-Dist: requests
Requires-Dist: bs4
